MANIFEST.in
README.rst
setup.py
cardsource/__init__.py
cardsource/cards.py
cardsource/deck.py
cardsource/errors.py
cardsource/hand.py
cardsource.egg-info/PKG-INFO
cardsource.egg-info/SOURCES.txt
cardsource.egg-info/dependency_links.txt
cardsource.egg-info/top_level.txt
cardsource/games/__init__.py
cardsource/games/blackjack/__init__.py
cardsource/games/blackjack/cards.py
cardsource/games/blackjack/deck.py
cardsource/games/blackjack/hand.py
cardsource/games/blackjack/shoe.py
docs/advanced.rst
docs/api.rst
docs/basic.rst
docs/changelog.rst
docs/contribute.rst
docs/index.rst
docs/install.rst
docs/introduction.rst
docs/performance.rst